py_it_crypto/__init__.py
py_it_crypto/globals.py
py_it_crypto/itcrypto.py
py_it_crypto/utils.py
py_it_crypto/crypto/__init__.py
py_it_crypto/crypto/decryption.py
py_it_crypto/crypto/encryption.py
py_it_crypto/logs/__init__.py
py_it_crypto/logs/access_log.py
py_it_crypto/logs/serializable.py
py_it_crypto/logs/shared_log.py
py_it_crypto/logs/signed_log.py
py_it_crypto/user/__init__.py
py_it_crypto/user/authenticatedUser.py
py_it_crypto/user/remoteUser.py
py_it_crypto/user/user.py
py_it_crypto-1.0.7.dist-info/METADATA
py_it_crypto-1.0.7.dist-info/WHEEL
py_it_crypto-1.0.7.dist-info/licenses/LICENSE
py_it_crypto-1.0.7.dist-info/RECORD
