Metadata-Version: 2.1
Name: py_it_crypto
Version: 1.0.7
Summary: E2EE for the inverse transparency toolchain
Author: Jonas Hagg
License-File: LICENSE
Classifier: License :: OSI Approved :: GNU General Public License v3 (GPLv3)
Classifier: Operating System :: OS Independent
Classifier: Programming Language :: Python :: 3
Requires-Python: >=3.7
Requires-Dist: jwcrypto~=1.4.2
Requires-Dist: pyopenssl~=22.1.0
